{
  "annotations": {
    "list": [
      {
        "builtIn": 1,
        "datasource": {
          "type": "grafana",
          "uid": "-- Grafana --"
        },
        "enable": true,
        "hide": true,
        "iconColor": "rgba(0, 211, 255, 1)",
        "name": "Annotations & Alerts",
        "type": "dashboard"
      }
    ]
  },
  "editable": true,
  "fiscalYearStartMonth": 0,
  "graphTooltip": 1,
  "id": null,
  "links": [],
  "panels": [
    {
      "collapsed": false,
      "gridPos": { "h": 1, "w": 24, "x": 0, "y": 0 },
      "id": 100,
      "title": "System Overview",
      "type": "row"
    },
    {
      "datasource": { "type": "prometheus", "uid": "PBFA97CFB590B2093" },
      "description": "System uptime in days",
      "fieldConfig": {
        "defaults": {
          "color": { "mode": "thresholds" },
          "mappings": [],
          "thresholds": {
            "mode": "absolute",
            "steps": [
              { "color": "red", "value": null },
              { "color": "orange", "value": 1 },
              { "color": "green", "value": 7 }
            ]
          },
          "unit": "d"
        },
        "overrides": []
      },
      "gridPos": { "h": 4, "w": 4, "x": 0, "y": 1 },
      "id": 1,
      "options": {
        "colorMode": "value",
        "graphMode": "none",
        "justifyMode": "auto",
        "orientation": "auto",
        "reduceOptions": { "calcs": ["lastNotNull"], "fields": "", "values": false },
        "textMode": "auto"
      },
      "pluginVersion": "10.2.0",
      "targets": [
        {
          "datasource": { "type": "prometheus", "uid": "PBFA97CFB590B2093" },
          "expr": "(time() - node_boot_time_seconds{instance=~\"$instance\"}) / 86400",
          "legendFormat": "Uptime",
          "refId": "A"
        }
      ],
      "title": "Uptime",
      "type": "stat"
    },
    {
      "datasource": { "type": "prometheus", "uid": "PBFA97CFB590B2093" },
      "description": "Number of CPU cores",
      "fieldConfig": {
        "defaults": {
          "color": { "mode": "thresholds" },
          "mappings": [],
          "thresholds": {
            "mode": "absolute",
            "steps": [{ "color": "blue", "value": null }]
          }
        },
        "overrides": []
      },
      "gridPos": { "h": 4, "w": 4, "x": 4, "y": 1 },
      "id": 2,
      "options": {
        "colorMode": "value",
        "graphMode": "none",
        "justifyMode": "auto",
        "orientation": "auto",
        "reduceOptions": { "calcs": ["lastNotNull"], "fields": "", "values": false },
        "textMode": "auto"
      },
      "pluginVersion": "10.2.0",
      "targets": [
        {
          "datasource": { "type": "prometheus", "uid": "PBFA97CFB590B2093" },
          "expr": "count(node_cpu_seconds_total{instance=~\"$instance\", mode=\"idle\"})",
          "legendFormat": "Cores",
          "refId": "A"
        }
      ],
      "title": "CPU Cores",
      "type": "stat"
    },
    {
      "datasource": { "type": "prometheus", "uid": "PBFA97CFB590B2093" },
      "description": "Total system memory",
      "fieldConfig": {
        "defaults": {
          "color": { "mode": "thresholds" },
          "mappings": [],
          "thresholds": {
            "mode": "absolute",
            "steps": [{ "color": "purple", "value": null }]
          },
          "unit": "bytes"
        },
        "overrides": []
      },
      "gridPos": { "h": 4, "w": 4, "x": 8, "y": 1 },
      "id": 3,
      "options": {
        "colorMode": "value",
        "graphMode": "none",
        "justifyMode": "auto",
        "orientation": "auto",
        "reduceOptions": { "calcs": ["lastNotNull"], "fields": "", "values": false },
        "textMode": "auto"
      },
      "pluginVersion": "10.2.0",
      "targets": [
        {
          "datasource": { "type": "prometheus", "uid": "PBFA97CFB590B2093" },
          "expr": "node_memory_MemTotal_bytes{instance=~\"$instance\"}",
          "legendFormat": "Total",
          "refId": "A"
        }
      ],
      "title": "Total Memory",
      "type": "stat"
    },
    {
      "datasource": { "type": "prometheus", "uid": "PBFA97CFB590B2093" },
      "description": "Total root filesystem size",
      "fieldConfig": {
        "defaults": {
          "color": { "mode": "thresholds" },
          "mappings": [],
          "thresholds": {
            "mode": "absolute",
            "steps": [{ "color": "orange", "value": null }]
          },
          "unit": "bytes"
        },
        "overrides": []
      },
      "gridPos": { "h": 4, "w": 4, "x": 12, "y": 1 },
      "id": 4,
      "options": {
        "colorMode": "value",
        "graphMode": "none",
        "justifyMode": "auto",
        "orientation": "auto",
        "reduceOptions": { "calcs": ["lastNotNull"], "fields": "", "values": false },
        "textMode": "auto"
      },
      "pluginVersion": "10.2.0",
      "targets": [
        {
          "datasource": { "type": "prometheus", "uid": "PBFA97CFB590B2093" },
          "expr": "node_filesystem_size_bytes{instance=~\"$instance\", mountpoint=\"/\", fstype!=\"rootfs\"}",
          "legendFormat": "Root FS",
          "refId": "A"
        }
      ],
      "title": "Root Filesystem",
      "type": "stat"
    },
    {
      "collapsed": false,
      "gridPos": { "h": 1, "w": 24, "x": 0, "y": 5 },
      "id": 101,
      "title": "CPU",
      "type": "row"
    },
    {
      "datasource": { "type": "prometheus", "uid": "PBFA97CFB590B2093" },
      "description": "Overall CPU utilization percentage",
      "fieldConfig": {
        "defaults": {
          "color": { "mode": "continuous-GrYlRd" },
          "mappings": [],
          "max": 100,
          "min": 0,
          "thresholds": {
            "mode": "absolute",
            "steps": [
              { "color": "green", "value": null },
              { "color": "yellow", "value": 60 },
              { "color": "red", "value": 85 }
            ]
          },
          "unit": "percent"
        },
        "overrides": []
      },
      "gridPos": { "h": 6, "w": 6, "x": 0, "y": 6 },
      "id": 5,
      "options": {
        "minVizHeight": 75,
        "minVizWidth": 75,
        "orientation": "auto",
        "reduceOptions": { "calcs": ["lastNotNull"], "fields": "", "values": false },
        "showThresholdLabels": false,
        "showThresholdMarkers": true,
        "sizing": "auto"
      },
      "pluginVersion": "10.2.0",
      "targets": [
        {
          "datasource": { "type": "prometheus", "uid": "PBFA97CFB590B2093" },
          "expr": "100 - (avg by(instance) (irate(node_cpu_seconds_total{instance=~\"$instance\", mode=\"idle\"}[5m])) * 100)",
          "legendFormat": "CPU Usage",
          "refId": "A"
        }
      ],
      "title": "CPU Usage",
      "type": "gauge"
    },
    {
      "datasource": { "type": "prometheus", "uid": "PBFA97CFB590B2093" },
      "description": "CPU usage broken down by mode over time",
      "fieldConfig": {
        "defaults": {
          "color": { "mode": "palette-classic" },
          "custom": {
            "axisBorderShow": false,
            "axisCenteredZero": false,
            "axisColorMode": "text",
            "axisLabel": "",
            "axisPlacement": "auto",
            "barAlignment": 0,
            "drawStyle": "line",
            "fillOpacity": 30,
            "gradientMode": "opacity",
            "hideFrom": { "legend": false, "tooltip": false, "viz": false },
            "insertNulls": false,
            "lineInterpolation": "smooth",
            "lineWidth": 2,
            "pointSize": 5,
            "scaleDistribution": { "type": "linear" },
            "showPoints": "never",
            "spanNulls": false,
            "stacking": { "group": "A", "mode": "normal" },
            "thresholdsStyle": { "mode": "off" }
          },
          "mappings": [],
          "max": 100,
          "min": 0,
          "thresholds": {
            "mode": "absolute",
            "steps": [{ "color": "green", "value": null }]
          },
          "unit": "percent"
        },
        "overrides": []
      },
      "gridPos": { "h": 6, "w": 18, "x": 6, "y": 6 },
      "id": 6,
      "options": {
        "legend": { "calcs": ["mean", "max"], "displayMode": "table", "placement": "right", "showLegend": true },
        "tooltip": { "mode": "multi", "sort": "desc" }
      },
      "pluginVersion": "10.2.0",
      "targets": [
        {
          "datasource": { "type": "prometheus", "uid": "PBFA97CFB590B2093" },
          "expr": "avg by (mode) (irate(node_cpu_seconds_total{instance=~\"$instance\", mode!=\"idle\"}[5m])) * 100",
          "legendFormat": "{{ mode }}",
          "refId": "A"
        }
      ],
      "title": "CPU Usage by Mode",
      "type": "timeseries"
    },
    {
      "datasource": { "type": "prometheus", "uid": "PBFA97CFB590B2093" },
      "description": "System load averages (1m, 5m, 15m)",
      "fieldConfig": {
        "defaults": {
          "color": { "mode": "palette-classic" },
          "custom": {
            "axisBorderShow": false,
            "axisCenteredZero": false,
            "axisColorMode": "text",
            "axisLabel": "Load",
            "axisPlacement": "auto",
            "drawStyle": "line",
            "fillOpacity": 10,
            "gradientMode": "none",
            "hideFrom": { "legend": false, "tooltip": false, "viz": false },
            "lineInterpolation": "smooth",
            "lineWidth": 2,
            "pointSize": 5,
            "scaleDistribution": { "type": "linear" },
            "showPoints": "never",
            "spanNulls": false,
            "stacking": { "group": "A", "mode": "none" },
            "thresholdsStyle": { "mode": "off" }
          },
          "mappings": [],
          "thresholds": {
            "mode": "absolute",
            "steps": [{ "color": "green", "value": null }]
          }
        },
        "overrides": []
      },
      "gridPos": { "h": 6, "w": 12, "x": 0, "y": 12 },
      "id": 7,
      "options": {
        "legend": { "calcs": ["mean", "lastNotNull"], "displayMode": "table", "placement": "bottom", "showLegend": true },
        "tooltip": { "mode": "multi", "sort": "desc" }
      },
      "pluginVersion": "10.2.0",
      "targets": [
        {
          "datasource": { "type": "prometheus", "uid": "PBFA97CFB590B2093" },
          "expr": "node_load1{instance=~\"$instance\"}",
          "legendFormat": "Load 1m",
          "refId": "A"
        },
        {
          "datasource": { "type": "prometheus", "uid": "PBFA97CFB590B2093" },
          "expr": "node_load5{instance=~\"$instance\"}",
          "legendFormat": "Load 5m",
          "refId": "B"
        },
        {
          "datasource": { "type": "prometheus", "uid": "PBFA97CFB590B2093" },
          "expr": "node_load15{instance=~\"$instance\"}",
          "legendFormat": "Load 15m",
          "refId": "C"
        }
      ],
      "title": "System Load Average",
      "type": "timeseries"
    },
    {
      "collapsed": false,
      "gridPos": { "h": 1, "w": 24, "x": 0, "y": 18 },
      "id": 102,
      "title": "Memory",
      "type": "row"
    },
    {
      "datasource": { "type": "prometheus", "uid": "PBFA97CFB590B2093" },
      "description": "Current memory utilization percentage",
      "fieldConfig": {
        "defaults": {
          "color": { "mode": "continuous-GrYlRd" },
          "mappings": [],
          "max": 100,
          "min": 0,
          "thresholds": {
            "mode": "absolute",
            "steps": [
              { "color": "green", "value": null },
              { "color": "yellow", "value": 60 },
              { "color": "red", "value": 85 }
            ]
          },
          "unit": "percent"
        },
        "overrides": []
      },
      "gridPos": { "h": 6, "w": 6, "x": 0, "y": 19 },
      "id": 8,
      "options": {
        "minVizHeight": 75,
        "minVizWidth": 75,
        "orientation": "auto",
        "reduceOptions": { "calcs": ["lastNotNull"], "fields": "", "values": false },
        "showThresholdLabels": false,
        "showThresholdMarkers": true,
        "sizing": "auto"
      },
      "pluginVersion": "10.2.0",
      "targets": [
        {
          "datasource": { "type": "prometheus", "uid": "PBFA97CFB590B2093" },
          "expr": "(1 - (node_memory_MemAvailable_bytes{instance=~\"$instance\"} / node_memory_MemTotal_bytes{instance=~\"$instance\"})) * 100",
          "legendFormat": "Memory Usage",
          "refId": "A"
        }
      ],
      "title": "Memory Usage",
      "type": "gauge"
    },
    {
      "datasource": { "type": "prometheus", "uid": "PBFA97CFB590B2093" },
      "description": "Memory usage breakdown over time",
      "fieldConfig": {
        "defaults": {
          "color": { "mode": "palette-classic" },
          "custom": {
            "axisBorderShow": false,
            "axisCenteredZero": false,
            "axisColorMode": "text",
            "axisLabel": "",
            "axisPlacement": "auto",
            "drawStyle": "line",
            "fillOpacity": 30,
            "gradientMode": "opacity",
            "hideFrom": { "legend": false, "tooltip": false, "viz": false },
            "insertNulls": false,
            "lineInterpolation": "smooth",
            "lineWidth": 2,
            "pointSize": 5,
            "scaleDistribution": { "type": "linear" },
            "showPoints": "never",
            "spanNulls": false,
            "stacking": { "group": "A", "mode": "normal" },
            "thresholdsStyle": { "mode": "off" }
          },
          "mappings": [],
          "thresholds": {
            "mode": "absolute",
            "steps": [{ "color": "green", "value": null }]
          },
          "unit": "bytes"
        },
        "overrides": []
      },
      "gridPos": { "h": 6, "w": 18, "x": 6, "y": 19 },
      "id": 9,
      "options": {
        "legend": { "calcs": ["mean", "lastNotNull"], "displayMode": "table", "placement": "right", "showLegend": true },
        "tooltip": { "mode": "multi", "sort": "desc" }
      },
      "pluginVersion": "10.2.0",
      "targets": [
        {
          "datasource": { "type": "prometheus", "uid": "PBFA97CFB590B2093" },
          "expr": "node_memory_MemTotal_bytes{instance=~\"$instance\"} - node_memory_MemAvailable_bytes{instance=~\"$instance\"}",
          "legendFormat": "Used",
          "refId": "A"
        },
        {
          "datasource": { "type": "prometheus", "uid": "PBFA97CFB590B2093" },
          "expr": "node_memory_Buffers_bytes{instance=~\"$instance\"}",
          "legendFormat": "Buffers",
          "refId": "B"
        },
        {
          "datasource": { "type": "prometheus", "uid": "PBFA97CFB590B2093" },
          "expr": "node_memory_Cached_bytes{instance=~\"$instance\"}",
          "legendFormat": "Cached",
          "refId": "C"
        },
        {
          "datasource": { "type": "prometheus", "uid": "PBFA97CFB590B2093" },
          "expr": "node_memory_MemAvailable_bytes{instance=~\"$instance\"}",
          "legendFormat": "Available",
          "refId": "D"
        }
      ],
      "title": "Memory Usage Over Time",
      "type": "timeseries"
    },
    {
      "collapsed": false,
      "gridPos": { "h": 1, "w": 24, "x": 0, "y": 25 },
      "id": 103,
      "title": "Disk & Filesystem",
      "type": "row"
    },
    {
      "datasource": { "type": "prometheus", "uid": "PBFA97CFB590B2093" },
      "description": "Filesystem usage by mount point",
      "fieldConfig": {
        "defaults": {
          "color": { "mode": "continuous-GrYlRd" },
          "mappings": [],
          "max": 100,
          "min": 0,
          "thresholds": {
            "mode": "absolute",
            "steps": [
              { "color": "green", "value": null },
              { "color": "yellow", "value": 70 },
              { "color": "red", "value": 85 }
            ]
          },
          "unit": "percent"
        },
        "overrides": []
      },
      "gridPos": { "h": 6, "w": 8, "x": 0, "y": 26 },
      "id": 10,
      "options": {
        "displayMode": "lcd",
        "maxVizHeight": 300,
        "minVizHeight": 16,
        "minVizWidth": 8,
        "namePlacement": "auto",
        "orientation": "horizontal",
        "reduceOptions": { "calcs": ["lastNotNull"], "fields": "", "values": false },
        "showUnfilled": true,
        "sizing": "auto",
        "valueMode": "color"
      },
      "pluginVersion": "10.2.0",
      "targets": [
        {
          "datasource": { "type": "prometheus", "uid": "PBFA97CFB590B2093" },
          "expr": "(1 - (node_filesystem_avail_bytes{instance=~\"$instance\", fstype!~\"tmpfs|overlay\"} / node_filesystem_size_bytes{instance=~\"$instance\", fstype!~\"tmpfs|overlay\"})) * 100",
          "legendFormat": "{{ mountpoint }}",
          "refId": "A"
        }
      ],
      "title": "Filesystem Usage",
      "type": "bargauge"
    },
    {
      "datasource": { "type": "prometheus", "uid": "PBFA97CFB590B2093" },
      "description": "Disk read/write throughput",
      "fieldConfig": {
        "defaults": {
          "color": { "mode": "palette-classic" },
          "custom": {
            "axisBorderShow": false,
            "axisCenteredZero": true,
            "axisColorMode": "text",
            "axisLabel": "",
            "axisPlacement": "auto",
            "drawStyle": "line",
            "fillOpacity": 20,
            "gradientMode": "none",
            "hideFrom": { "legend": false, "tooltip": false, "viz": false },
            "lineInterpolation": "smooth",
            "lineWidth": 2,
            "pointSize": 5,
            "scaleDistribution": { "type": "linear" },
            "showPoints": "never",
            "spanNulls": false,
            "stacking": { "group": "A", "mode": "none" },
            "thresholdsStyle": { "mode": "off" }
          },
          "mappings": [],
          "thresholds": {
            "mode": "absolute",
            "steps": [{ "color": "green", "value": null }]
          },
          "unit": "Bps"
        },
        "overrides": []
      },
      "gridPos": { "h": 6, "w": 16, "x": 8, "y": 26 },
      "id": 11,
      "options": {
        "legend": { "calcs": ["mean", "max"], "displayMode": "table", "placement": "bottom", "showLegend": true },
        "tooltip": { "mode": "multi", "sort": "desc" }
      },
      "pluginVersion": "10.2.0",
      "targets": [
        {
          "datasource": { "type": "prometheus", "uid": "PBFA97CFB590B2093" },
          "expr": "irate(node_disk_read_bytes_total{instance=~\"$instance\", device!~\"dm-.*\"}[5m])",
          "legendFormat": "Read {{ device }}",
          "refId": "A"
        },
        {
          "datasource": { "type": "prometheus", "uid": "PBFA97CFB590B2093" },
          "expr": "-irate(node_disk_written_bytes_total{instance=~\"$instance\", device!~\"dm-.*\"}[5m])",
          "legendFormat": "Write {{ device }}",
          "refId": "B"
        }
      ],
      "title": "Disk I/O Throughput",
      "type": "timeseries"
    },
    {
      "collapsed": false,
      "gridPos": { "h": 1, "w": 24, "x": 0, "y": 32 },
      "id": 104,
      "title": "Network",
      "type": "row"
    },
    {
      "datasource": { "type": "prometheus", "uid": "PBFA97CFB590B2093" },
      "description": "Network traffic received and transmitted",
      "fieldConfig": {
        "defaults": {
          "color": { "mode": "palette-classic" },
          "custom": {
            "axisBorderShow": false,
            "axisCenteredZero": true,
            "axisColorMode": "text",
            "axisLabel": "",
            "axisPlacement": "auto",
            "drawStyle": "line",
            "fillOpacity": 20,
            "gradientMode": "opacity",
            "hideFrom": { "legend": false, "tooltip": false, "viz": false },
            "lineInterpolation": "smooth",
            "lineWidth": 2,
            "pointSize": 5,
            "scaleDistribution": { "type": "linear" },
            "showPoints": "never",
            "spanNulls": false,
            "stacking": { "group": "A", "mode": "none" },
            "thresholdsStyle": { "mode": "off" }
          },
          "mappings": [],
          "thresholds": {
            "mode": "absolute",
            "steps": [{ "color": "green", "value": null }]
          },
          "unit": "bps"
        },
        "overrides": []
      },
      "gridPos": { "h": 8, "w": 24, "x": 0, "y": 33 },
      "id": 12,
      "options": {
        "legend": { "calcs": ["mean", "max"], "displayMode": "table", "placement": "bottom", "showLegend": true },
        "tooltip": { "mode": "multi", "sort": "desc" }
      },
      "pluginVersion": "10.2.0",
      "targets": [
        {
          "datasource": { "type": "prometheus", "uid": "PBFA97CFB590B2093" },
          "expr": "irate(node_network_receive_bytes_total{instance=~\"$instance\", device!~\"lo|veth.*|docker.*|br-.*\"}[5m]) * 8",
          "legendFormat": "Receive {{ device }}",
          "refId": "A"
        },
        {
          "datasource": { "type": "prometheus", "uid": "PBFA97CFB590B2093" },
          "expr": "-irate(node_network_transmit_bytes_total{instance=~\"$instance\", device!~\"lo|veth.*|docker.*|br-.*\"}[5m]) * 8",
          "legendFormat": "Transmit {{ device }}",
          "refId": "B"
        }
      ],
      "title": "Network Traffic",
      "type": "timeseries"
    }
  ],
  "preload": false,
  "refresh": "30s",
  "schemaVersion": 39,
  "tags": ["node-exporter", "linux", "system"],
  "templating": {
    "list": [
      {
        "current": { "selected": false, "text": "All", "value": "$__all" },
        "datasource": { "type": "prometheus", "uid": "PBFA97CFB590B2093" },
        "definition": "label_values(node_uname_info, instance)",
        "includeAll": true,
        "label": "Instance",
        "multi": false,
        "name": "instance",
        "options": [],
        "query": "label_values(node_uname_info, instance)",
        "refresh": 2,
        "regex": "",
        "sort": 1,
        "type": "query"
      }
    ]
  },
  "time": { "from": "now-6h", "to": "now" },
  "timepicker": {},
  "timezone": "browser",
  "title": "Linux System Dashboard",
  "uid": "node-exporter-system",
  "version": 1
}
